yubi
