Metadata-Version: 2.1
Name: awsume-yubi-plugin
Version: 0.1.2
Summary: Plugin to use a Yubikey with awsume
Home-page: https://github.com/kylejwatson/awsume-yubi-plugin
Author: Kyle Watson
Author-email: kyle.watson@woodwing.com
License: MIT
Platform: UNKNOWN
License-File: LICENSE.txt
